{
    "Tiempo": "Finalizado",
    "Equipo1": "Racing Club",
    "Equipo2": "Def y Justicia",
    "Resultado": {
        "Equipo1": "4",
        "Equipo2": "3"
    },
    "Fecha": "",
    "Estadio": "Presidente Perón (Cilindro de Avellaneda)",
    "Arbitro": "Pablo Dóvalo",
    "TV": "TV ARG: TNT SPORTS PACK PREMIUM",
    "Resumen": "https://www.youtube.com/embed/lM3bL8n4N2I",
    "formacion1": {
        "equipo": "Racing Club",
        "titulares": [
            {
                "Pos": "Pos",
                "N°": "N°",
                "Jugador": "Jugador",
                "Edad": "Edad",
                "Alt(cm)": "Alt(cm)",
                "Imagenes": []
            },
            {
                "Pos": "ARQ",
                "N°": "21",
                "Jugador": "Gabriel Arias",
                "Edad": "37",
                "Alt(cm)": "188",
                "Imagenes": [
                    "../images/cuadrados/chile.gif"
                ]
            },
            {
                "Pos": "DEF",
                "N°": "15",
                "Jugador": "Gastón Martirena",
                "Edad": "24",
                "Alt(cm)": "173",
                "Imagenes": [
                    "../images/cuadrados/uruguay.gif",
                    "../images/pelo.png"
                ]
            },
            {
                "Pos": "DEF",
                "N°": "6",
                "Jugador": "Nazareno Colombo",
                "Edad": "25",
                "Alt(cm)": "184",
                "Imagenes": [
                    "../images/cuadrados/argentina.gif",
                    "../images/lesion.png",
                    "../images/flechaout.png"
                ]
            },
            {
                "Pos": "DEF",
                "N°": "2",
                "Jugador": "Agustín García Basso",
                "Edad": "32",
                "Alt(cm)": "178",
                "Imagenes": [
                    "../images/cuadrados/argentina.gif"
                ]
            },
            {
                "Pos": "DEF",
                "N°": "34",
                "Jugador": "Facundo Mura",
                "Edad": "25",
                "Alt(cm)": "174",
                "Imagenes": [
                    "../images/cuadrados/argentina.gif"
                ]
            },
            {
                "Pos": "MED",
                "N°": "36",
                "Jugador": "Bruno Zuculini",
                "Edad": "31",
                "Alt(cm)": "182",
                "Imagenes": [
                    "../images/cuadrados/argentina.gif"
                ]
            },
            {
                "Pos": "MED",
                "N°": "28",
                "Jugador": "Santiago Solari",
                "Edad": "26",
                "Alt(cm)": "178",
                "Imagenes": [
                    "../images/cuadrados/argentina.gif"
                ]
            },
            {
                "Pos": "MED",
                "N°": "5",
                "Jugador": "Juan Nardoni",
                "Edad": "22",
                "Alt(cm)": "179",
                "Imagenes": [
                    "../images/cuadrados/argentina.gif"
                ]
            },
            {
                "Pos": "MED",
                "N°": "32",
                "Jugador": "Agustín Almendra",
                "Edad": "24",
                "Alt(cm)": "182",
                "Imagenes": [
                    "../images/cuadrados/argentina.gif",
                    "../images/flechaout.png"
                ]
            },
            {
                "Pos": "MED",
                "N°": "12",
                "Jugador": "Luciano Vietto",
                "Edad": "30",
                "Alt(cm)": "173",
                "Imagenes": [
                    "../images/cuadrados/argentina.gif",
                    "../images/flechaout.png"
                ]
            },
            {
                "Pos": "DEL",
                "N°": "9",
                "Jugador": "Adrián Martínez",
                "Edad": "32",
                "Alt(cm)": "181",
                "Imagenes": [
                    "../images/cuadrados/argentina.gif",
                    "../images/pelo.png",
                    "../images/pelo.png",
                    "../images/flechaout.png"
                ]
            }
        ],
        "dt": {
            "Pos": "DT",
            "Nombre": "Gustavo Costas",
            "Edad": "61",
            "Imagen": "../images/cuadrados/argentina.gif"
        },
        "suplentes": [
            {
                "Pos": "ARQ",
                "N°": "25",
                "Jugador": "Facundo Cambeses",
                "Edad": "27",
                "Alt(cm)": "186",
                "Imagenes": [
                    "../images/cuadrados/argentina.gif"
                ]
            },
            {
                "Pos": "DEF",
                "N°": "20",
                "Jugador": "Germán Conti",
                "Edad": "30",
                "Alt(cm)": "192",
                "Imagenes": [
                    "../images/cuadrados/argentina.gif"
                ]
            },
            {
                "Pos": "DEF",
                "N°": "19",
                "Jugador": "Juan Manuel Elordi",
                "Edad": "30",
                "Alt(cm)": "176",
                "Imagenes": [
                    "../images/cuadrados/argentina.gif"
                ]
            },
            {
                "Pos": "DEF",
                "N°": "30",
                "Jugador": "Leonardo Sigali",
                "Edad": "37",
                "Alt(cm)": "180",
                "Imagenes": [
                    "../images/cuadrados/argentina.gif",
                    "../images/flechain.png"
                ]
            },
            {
                "Pos": "DEF",
                "N°": "43",
                "Jugador": "Gonzalo Escudero",
                "Edad": "17",
                "Alt(cm)": "180",
                "Imagenes": [
                    "../images/cuadrados/argentina.gif"
                ]
            },
            {
                "Pos": "MED",
                "N°": "8",
                "Jugador": "Juan Quintero",
                "Edad": "31",
                "Alt(cm)": "168",
                "Imagenes": [
                    "../images/cuadrados/colombia.gif",
                    "../images/flechain.png"
                ]
            },
            {
                "Pos": "MED",
                "N°": "13",
                "Jugador": "Santiago Sosa",
                "Edad": "25",
                "Alt(cm)": "179",
                "Imagenes": [
                    "../images/cuadrados/argentina.gif"
                ]
            },
            {
                "Pos": "MED",
                "N°": "16",
                "Jugador": "Martín Barrios",
                "Edad": "25",
                "Alt(cm)": "177",
                "Imagenes": [
                    "../images/cuadrados/uruguay.gif"
                ]
            },
            {
                "Pos": "MED",
                "N°": "22",
                "Jugador": "Baltasar Rodriguez",
                "Edad": "21",
                "Alt(cm)": "173",
                "Imagenes": [
                    "../images/cuadrados/argentina.gif",
                    "../images/flechain.png"
                ]
            },
            {
                "Pos": "DEL",
                "N°": "7",
                "Jugador": "Maximiliano Salas",
                "Edad": "26",
                "Alt(cm)": "174",
                "Imagenes": [
                    "../images/cuadrados/argentina.gif",
                    "../images/flechain.png",
                    "../images/pelo.png"
                ]
            },
            {
                "Pos": "DEL",
                "N°": "18",
                "Jugador": "Agustín Urzi",
                "Edad": "24",
                "Alt(cm)": "168",
                "Imagenes": [
                    "../images/cuadrados/argentina.gif"
                ]
            },
            {
                "Pos": "DEL",
                "N°": "41",
                "Jugador": "Ramiro Degregorio",
                "Edad": "21",
                "Alt(cm)": "170",
                "Imagenes": [
                    "../images/cuadrados/argentina.gif"
                ]
            }
        ],
        "Goles": "30' G. Martirena; 40' A. Martinez; 45(+1)' A. Martinez; 84' M. Salas;",
        "Amarillas": "",
        "Rojas": "",
        "Cambios": "59' J. Quintero ⇆ L. Vietto; 59' B. Rodriguez ⇆ A. Almendra; 76' M. Salas ⇆ A. Martinez; 78' L. Sigali ⇆ N. Colombo (Lesion);"
    },
    "formacion2": {
        "equipo": "Def y Justicia",
        "titulares": [
            {
                "Pos": "Pos",
                "N°": "N°",
                "Jugador": "Jugador",
                "Edad": "Edad",
                "Alt(cm)": "Alt(cm)",
                "Imagenes": []
            },
            {
                "Pos": "ARQ",
                "N°": "23",
                "Jugador": "Enrique Bologna",
                "Edad": "42",
                "Alt(cm)": "188",
                "Imagenes": [
                    "../images/cuadrados/argentina.gif"
                ]
            },
            {
                "Pos": "DEF",
                "N°": "38",
                "Jugador": "Tobías Rubio",
                "Edad": "20",
                "Alt(cm)": "175",
                "Imagenes": [
                    "../images/cuadrados/argentina.gif"
                ]
            },
            {
                "Pos": "DEF",
                "N°": "28",
                "Jugador": "Victor Aguilera",
                "Edad": "35",
                "Alt(cm)": "187",
                "Imagenes": [
                    "../images/cuadrados/argentina.gif",
                    "../images/flechaout.png"
                ]
            },
            {
                "Pos": "DEF",
                "N°": "21",
                "Jugador": "Santiago Ramos",
                "Edad": "22",
                "Alt(cm)": "186",
                "Imagenes": [
                    "../images/cuadrados/argentina.gif"
                ]
            },
            {
                "Pos": "DEF",
                "N°": "3",
                "Jugador": "Alexis Soto",
                "Edad": "30",
                "Alt(cm)": "172",
                "Imagenes": [
                    "../images/cuadrados/argentina.gif"
                ]
            },
            {
                "Pos": "MED",
                "N°": "17",
                "Jugador": "Gabriel Alanís",
                "Edad": "30",
                "Alt(cm)": "186",
                "Imagenes": [
                    "../images/cuadrados/argentina.gif",
                    "../images/flechaout.png"
                ]
            },
            {
                "Pos": "MED",
                "N°": "5",
                "Jugador": "Kevin Gutiérrez",
                "Edad": "27",
                "Alt(cm)": "168",
                "Imagenes": [
                    "../images/cuadrados/argentina.gif"
                ]
            },
            {
                "Pos": "MED",
                "N°": "35",
                "Jugador": "Benjamín Schamine",
                "Edad": "20",
                "Alt(cm)": "178",
                "Imagenes": [
                    "../images/cuadrados/argentina.gif",
                    "../images/flechaout.png"
                ]
            },
            {
                "Pos": "MED",
                "N°": "27",
                "Jugador": "Luciano Herrera",
                "Edad": "28",
                "Alt(cm)": "180",
                "Imagenes": [
                    "../images/cuadrados/argentina.gif",
                    "../images/flechaout.png"
                ]
            },
            {
                "Pos": "DEL",
                "N°": "16",
                "Jugador": "Aaron Molinas",
                "Edad": "24",
                "Alt(cm)": "175",
                "Imagenes": [
                    "../images/cuadrados/argentina.gif",
                    "../images/pelo.png"
                ]
            },
            {
                "Pos": "DEL",
                "N°": "9",
                "Jugador": "Juan Miritello",
                "Edad": "25",
                "Alt(cm)": "183",
                "Imagenes": [
                    "../images/cuadrados/argentina.gif",
                    "../images/flechaout.png"
                ]
            }
        ],
        "dt": {
            "Pos": "DT",
            "Nombre": "Pablo De Muner",
            "Edad": "43",
            "Imagen": "../images/cuadrados/argentina.gif"
        },
        "suplentes": [
            {
                "Pos": "ARQ",
                "N°": "22",
                "Jugador": "Cristopher Fiermarin",
                "Edad": "26",
                "Alt(cm)": "189",
                "Imagenes": [
                    "../images/cuadrados/uruguay.gif"
                ]
            },
            {
                "Pos": "DEF",
                "N°": "14",
                "Jugador": "Ezequiel Cannavo",
                "Edad": "22",
                "Alt(cm)": "181",
                "Imagenes": [
                    "../images/cuadrados/argentina.gif"
                ]
            },
            {
                "Pos": "DEF",
                "N°": "18",
                "Jugador": "Ignacio Galván",
                "Edad": "22",
                "Alt(cm)": "177",
                "Imagenes": [
                    "../images/cuadrados/argentina.gif"
                ]
            },
            {
                "Pos": "DEF",
                "N°": "6",
                "Jugador": "Lucas Ferreira",
                "Edad": "24",
                "Alt(cm)": "187",
                "Imagenes": [
                    "../images/cuadrados/uruguay.gif"
                ]
            },
            {
                "Pos": "DEF",
                "N°": "4",
                "Jugador": "Tiago Ferreyra",
                "Edad": "22",
                "Alt(cm)": "",
                "Imagenes": [
                    "../images/cuadrados/argentina.gif"
                ]
            },
            {
                "Pos": "MED",
                "N°": "8",
                "Jugador": "Julián López",
                "Edad": "24",
                "Alt(cm)": "182",
                "Imagenes": [
                    "../images/cuadrados/argentina.gif"
                ]
            },
            {
                "Pos": "MED",
                "N°": "25",
                "Jugador": "César Pérez",
                "Edad": "21",
                "Alt(cm)": "176",
                "Imagenes": [
                    "../images/cuadrados/chile.gif",
                    "../images/flechain.png"
                ]
            },
            {
                "Pos": "MED",
                "N°": "33",
                "Jugador": "Nicolás Palavecino",
                "Edad": "21",
                "Alt(cm)": "186",
                "Imagenes": [
                    "../images/cuadrados/argentina.gif"
                ]
            },
            {
                "Pos": "MED",
                "N°": "30",
                "Jugador": "Kevin López",
                "Edad": "22",
                "Alt(cm)": "",
                "Imagenes": [
                    "../images/cuadrados/argentina.gif",
                    "../images/flechain.png"
                ]
            },
            {
                "Pos": "DEL",
                "N°": "10",
                "Jugador": "Rodrigo Bogarín",
                "Edad": "27",
                "Alt(cm)": "180",
                "Imagenes": [
                    "../images/cuadrados/paraguay.gif",
                    "../images/flechain.png"
                ]
            },
            {
                "Pos": "DEL",
                "N°": "37",
                "Jugador": "Matías Ramírez",
                "Edad": "25",
                "Alt(cm)": "175",
                "Imagenes": [
                    "../images/cuadrados/argentina.gif",
                    "../images/flechain.png",
                    "../images/pelo.png"
                ]
            },
            {
                "Pos": "DEL",
                "N°": "7",
                "Jugador": "Abiel Osorio",
                "Edad": "22",
                "Alt(cm)": "182",
                "Imagenes": [
                    "../images/cuadrados/argentina.gif",
                    "../images/flechain.png",
                    "../images/pelo.png"
                ]
            }
        ],
        "Goles": "70' M. Ramirez; 76' A. Osorio (pen.); 90(+2)' A. Molinas;",
        "Amarillas": "",
        "Rojas": "",
        "Cambios": "45' C. Perez ⇆ B. Schamine; 45' A. Osorio ⇆ J. Miritello; 45' M. Ramirez ⇆ L. Herrera; 66' K. Lopez ⇆ G. Alanis; 80' R. Bogarin ⇆ V. Aguilera;"
    },
    "Posesión": {
        "Equipo1": "44%",
        "Equipo2": "56%"
    },
    "Tiros efectivos al arco": {
        "Equipo1": "5",
        "Equipo2": "7"
    },
    "Tiros al arco": {
        "Equipo1": "15",
        "Equipo2": "20"
    },
    "Fouls Cometidos": {
        "Equipo1": "13",
        "Equipo2": "8"
    },
    "Corners": {
        "Equipo1": "4",
        "Equipo2": "8"
    }
}